deb_pack/__init__.py
deb_pack/context.py
deb_pack/main.py
deb_pack/services.py
deb_pack-0.1.2.dist-info/LICENSE
deb_pack-0.1.2.dist-info/METADATA
deb_pack-0.1.2.dist-info/WHEEL
deb_pack-0.1.2.dist-info/entry_points.txt
deb_pack-0.1.2.dist-info/top_level.txt
deb_pack-0.1.2.dist-info/RECORD
