Metadata-Version: 2.1
Name: deb-pack
Version: 0.1.2
Summary: Debian packaging tool
Home-page: https://github.com/mattj23/deb-pack
Author: Matthew Jarvis
Author-email: mattj23@gmail.com
Classifier: Programming Language :: Python :: 3
Classifier: License :: OSI Approved :: MIT License
Classifier: Operating System :: OS Independent
Requires-Python: >=3.8
License-File: LICENSE
Requires-Dist: click >=8.1.3
Requires-Dist: aptly-api-client >=0.2.4
